odoo/addons/stock_picking_report_valued/README.rst
odoo/addons/stock_picking_report_valued/__init__.py
odoo/addons/stock_picking_report_valued/__manifest__.py
odoo/addons/stock_picking_report_valued/i18n/es.po
odoo/addons/stock_picking_report_valued/i18n/hr.po
odoo/addons/stock_picking_report_valued/i18n/stock_picking_report_valued.pot
odoo/addons/stock_picking_report_valued/models/__init__.py
odoo/addons/stock_picking_report_valued/models/res_partner.py
odoo/addons/stock_picking_report_valued/models/stock_move_line.py
odoo/addons/stock_picking_report_valued/models/stock_picking.py
odoo/addons/stock_picking_report_valued/report/stock_picking_report_valued.xml
odoo/addons/stock_picking_report_valued/static/description/icon.png
odoo/addons/stock_picking_report_valued/tests/__init__.py
odoo/addons/stock_picking_report_valued/tests/test_stock_picking_valued.py
odoo/addons/stock_picking_report_valued/views/res_partner_view.xml
odoo11_addon_stock_picking_report_valued-11.0.1.0.1.dist-info/METADATA
odoo11_addon_stock_picking_report_valued-11.0.1.0.1.dist-info/RECORD
odoo11_addon_stock_picking_report_valued-11.0.1.0.1.dist-info/WHEEL
odoo11_addon_stock_picking_report_valued-11.0.1.0.1.dist-info/top_level.txt
